light_uniquebots/__init__.py
light_uniquebots-1.0.0.dist-info/LICENSE
light_uniquebots-1.0.0.dist-info/METADATA
light_uniquebots-1.0.0.dist-info/WHEEL
light_uniquebots-1.0.0.dist-info/top_level.txt
light_uniquebots-1.0.0.dist-info/RECORD
