Metadata-Version: 2.1
Name: light-uniquebots
Version: 1.0.0
Summary: UniqueBots를 위한 길드수 업뎃만 하는 모듈
Home-page: https://github.com/eunwoo1104/light-uniquebots
Author: eunwoo1104
Author-email: sions04@naver.com
License: UNKNOWN
Platform: UNKNOWN
Classifier: Programming Language :: Python :: 3
Requires-Python: >=3.6
